commtrack/__init__.py
commtrack/chain.py
commtrack/cli.py
commtrack/link.py
commtrack/parser.py
commtrack/common/__init__.py
commtrack/common/exceptions.py
commtrack/constants/__init__.py
commtrack/constants/chain.py
commtrack/constants/links.py
commtrack/exceptions/__init__.py
commtrack/exceptions/usage.py
commtrack/gerrit/__init__.py
commtrack/gerrit/constants.py
commtrack/gerrit/exceptions.py
commtrack/git/__init__.py
commtrack/git/constants.py
commtrack/git/exceptions.py
commtrack/links/__init__.py
commtrack/links/gerrit.py
commtrack/links/git.py
commtrack/plugins/__init__.py
commtrack/plugins/openstack.py
commtrack-0.0.1.dev21.dist-info/AUTHORS
commtrack-0.0.1.dev21.dist-info/LICENSE
commtrack-0.0.1.dev21.dist-info/METADATA
commtrack-0.0.1.dev21.dist-info/WHEEL
commtrack-0.0.1.dev21.dist-info/entry_points.txt
commtrack-0.0.1.dev21.dist-info/pbr.json
commtrack-0.0.1.dev21.dist-info/top_level.txt
commtrack-0.0.1.dev21.dist-info/RECORD
